{
  "version-0.1.0-docs": {
    "Overview": [
      "version-0.1.0-overview/navigation"
    ],
    "Getting Started": [
      "version-0.1.0-getting-started/quick-start"
    ],
    "Components": [
      {
        "Desktop": [
          "components/desktop/attachment",
          "components/desktop/button",
          "components/desktop/checkbox",
          "components/desktop/date-time",
          "components/desktop/dialog",
          "components/desktop/dropdown",
          "components/desktop/editable-table",
          "components/desktop/icon-button",
          "components/desktop/multiple-choice",
          "components/desktop/notify-popup",
          "components/desktop/radio-button",
          "components/desktop/readable-table",
          "components/desktop/spinner",
          "components/desktop/text",
          "components/desktop/text-area"
        ],
        "Mobile": [
          "components/mobile/button"
        ]
      }
    ]
  }
}
